modefit/__init__.py
modefit/baseobjects.py
modefit/basics.py
modefit/bimodal.py
modefit/unimodal.py
modefit/utils.py
modefit-0.4.2.dist-info/METADATA
modefit-0.4.2.dist-info/WHEEL
modefit-0.4.2.dist-info/top_level.txt
modefit-0.4.2.dist-info/RECORD
