Metadata-Version: 2.1
Name: modefit
Version: 0.4.2
Summary: modefit: Simple minuit<->mcmc fitting tools.
Home-page: https://github.com/MickaelRigault/modefit/
Download-URL: https://github.com/MickaelRigault/modefit/tarball/0.4
Author: Mickael Rigault
Author-email: mrigault@physik.hu-berlin.de
Maintainer: Mickael Rigault
Maintainer-email: mrigault@physik.hu-berlin.de
License: BSD (3-clause)
Classifier: Intended Audience :: Science/Research
Classifier: Programming Language :: Python :: 2.7
Classifier: Programming Language :: Python :: 3.5
Classifier: License :: OSI Approved :: BSD License
Classifier: Topic :: Scientific/Engineering :: Astronomy
Classifier: Operating System :: POSIX
Classifier: Operating System :: Unix
Classifier: Operating System :: MacOS
Requires-Dist: corner
Requires-Dist: iminuit >=2.0.0
Requires-Dist: matplotlib
Requires-Dist: numpy >=1.21.6
Requires-Dist: propobject >=0.1.3
Requires-Dist: scipy >=0.16.0
